{
  "itemCode": "Z_SKT_1778385559265_945",
  "productName": "착신전환_Voice_only",
  "carrier": "SKT",
  "category": "통화_메시지",
  "description": "",
  "content": {
    "details": "<div class=\"divDetailInfoContents adaptive-visualization\" data-contentidx=\"1\" style=\"display: none;\">\n                <div class=\"adaptive-belt-1000\">\n                    <div class=\"adaptive-belt-w1000\"><div class=\"prCont-txt\"><ul> \n<li>이용요금 : 월정액 990원(부가세 포함)</li>  \n<li>서비스 해지 시 요금은 일할 과금됩니다. </li>    \n<li>이용정지 및 일시정지할 경우 수신 할 수 있는 기간 중에는 사용 요금이 정상 부과됩니다.</li>  \n<li>착신전환 설정(*71) 시 착신전환 가입한 본인의 휴대폰으로 설정을 안내하는 SMS가 전달됩니다.<br>(SMS예시 : SKT&gt;[착신전환]010AAAABBBB님이 요청하신 010XXXXYYYY번으로 등록되었습니다)</li></ul></div></div>\n                </div>\n            </div>",
    "usageGuidelines": "<div class=\"divDetailInfoContents adaptive-visualization\" data-contentidx=\"2\" style=\"display: none;\">\n                <div class=\"adaptive-belt-1000\">\n                    <div class=\"adaptive-belt-w1000\"> <!-- ##### admin 등록 영역 ##### -->                            <div class=\"prCont-txt\">\n                                <table width=\"100%\" border=\"1\" summary=\"가입/해지 안내 - 유형, 가입/해지 경로, 방법으로 구성되어있습니다.\"><thead><tr><th scope=\"col\" width=\"20%\">유형</th><th scope=\"col\" width=\"30%\">가입/해지 경로</th><th scope=\"col\" width=\"50%\">방법</th></tr></thead><thead></thead><tbody><tr><th scope=\"row\" rowspan=\"3\">가입</th><td>T world 홈페이지/앱</td><td>T world &gt; '착신전환(Voice only)' 검색 &gt; 자세히 보기 &gt; 인증 후 가입</td></tr><tr><td>SKT 고객센터</td><td>02-1599-0011 /<br>SK 텔레콤 휴대폰으로 지역번호없이 114</td></tr><tr><td>SK텔레콤 지점/대리점</td><td>-</td></tr><tr><th scope=\"row\" rowspan=\"3\">해지</th><td>T world 홈페이지/앱</td><td>T world &gt; '착신전환(Voice only)' 검색 &gt; 자세히 보기</td></tr><tr><td>SKT 고객센터</td><td>02-1599-0011 /<br>SK 텔레콤 휴대폰으로 지역번호없이 114</td></tr><tr><td>SK텔레콤 지점/대리점 </td><td>-</td></tr></tbody></table>\n                            </div><!-- //##### admin 등록 영역 ##### --></div>\n                </div>\n            </div>\n<hr class=\"section-divider\">\n<div class=\"divDetailInfoContents adaptive-visualization\" data-contentidx=\"4\" style=\"display: none;\">\n                <div class=\"adaptive-belt-1000\">\n                    <div class=\"adaptive-belt-w1000\"><div class=\"prCont-txt\">\n                                <!-- 200227 [OP002-6986] 수정_03 -->\n                                \n<ul>\n                                    \n<li>등록<br>- *71 +착신전환 희망번호+통화버튼을 누르십시오.<br>&nbsp; ex) *71 + 010-1234-5678 +통화<br>- *71 + 064-1234-5678 +통화<br>- 확인 음을 들으신 후종료를 누르시면 됩니다.<br>- 등록완료 후 착신전환 가입한 본인의 휴대폰으로&nbsp;설정 사실을 안내하는 SMS가 전달됩니다.</li>\n                                    \n<li>해제<br>- *73 +통화 버튼을 누르십시오.<br>- 확인 음을 들으신 후종료를 누르시면 됩니다.</li>    \n                                    \n<li>착신전환 해제 후 가입한 본인의 휴대폰으로 해제되었음을 안내하는 SMS가 전달됩니다.</li>    \n                                    \n<li>식별번호(010 등)또는 지역번호를 반드시 입력해야 합니다.<br>단, 위의 특번은 국내에서만 이용 가능하며, 다른 전화 및 해외 등에서 이용 시 리모콘 서비스 가입 후 설정/해제가 가능합니다.</li>    \n                                    \n<li>리모콘(010-5200-8282)에서 착신 희망번호를 등록,해제하실 수 있습니다.</li>    \n                                    \n<li>리모콘 사용방법 : <br>- 010-5200-8282 + 통화 &gt; 휴대폰번호입력 &gt; 비밀번호입력 &gt; 1. 착신전환 -&gt; 1. 설정 / 2. 해제 선택</li>\n                                \n</ul>\n                                <!-- //200227 [OP002-6986] 수정_03 --></div></div>\n                </div>\n            </div>",
    "notices": "<div class=\"divDetailInfoContents adaptive-visualization\" data-contentidx=\"3\" style=\"display: none;\">\n                <div class=\"adaptive-belt-1000\">\n                    <div class=\"adaptive-belt-w1000\"><!-- ##### admin 등록 영역 ##### -->                            <div class=\"prCont-txt\">\n                                <h3>유의사항</h3>\n                                \n<ul>\n                                    \n<li>설정을 해제(*73+통화)한 경우에도 이용요금은 부과되므로, 이용을 원치 않는 경우 서비스를 해지하시기 바랍니다</li>    \n                                    \n<li>착신전환일반에 가입되어 있는 경우 착신전환(Voice only) 가입 시 착신전환일반 서비스는 해지되며 자동연결서비스는 함께 가입은 가능하나 동시에 이용은 불가합니다.</li>    \n                                    \n<li>서비스 제공목적 이외의 용도로 사용하는 경우 부가 서비스 해지 또는 휴대폰 번호의 이용정지/직권 해지 등 이용이 제한될 수 있습니다.</li>    \n                                    \n<li>금융거래 및 본인인증 등을 위한 ARS인증 통화에 대해서는 착신전환이 되지 않을 수 있습니다.</li>    \n                                    \n<li>수신자(착신전환 설정된 번호)가 원하지 않는 통화에 대해서는 서비스에 등록된 번호를 삭제할 수 있습니다.</li>    \n                                    \n<li>등록할 수 있는 번호유형<br>- 휴대폰번호(010), 유선 시내전화 가입자번호(02 ~ 064), 무선호출번호(012,015), 무선특수망번호(0130~0132), 인터넷전화번호(070)</li>    \n                                    \n<li>등록할 수 없는 번호유형<br>- 특수번호(예:1YY, 1YYY, 지역번호+1YY, 지역번호+1YYY 등), 국제전화번호(예:00X, 003YY, 007YY 등), 공통서비스식별번호(예: 030, 050, 060, 080 등) , 대표번호(예:14XX, 15XX,16XX, 18XX, 지역번호+15XX, 지역번호+16XX 등)</li>\n                                \n</ul>\n                                <h3>통화연결형서비스 상한정지관련 안내</h3>\n                                \n<ul>\n                                    \n<li>주요 내용<br>- 다른 전화로 연결되는 통화는 월270분까지 이용할 수 있으며&nbsp;이후 부가 서비스 이용이 정지됩니다.</li>\n                                    \n<li>추가이용 방법<br>- 고객센터(휴대폰에서114 -무료), 온라인 T world 에서 “착신전환일반 상한정지”서비스를 해지하시면 추가이용을 할 수 있습니다.</li>\n                                    \n<li>단, 19세 미만의 미성년자 또는 팅요금제 사용자는 해지되지 않습니다.<br>- 추가 이용 신청 시 무료사용량을 포함하여 음성통화 착신전환은&nbsp;최대1000분까지 이용할 수 있습니다.</li>\n                                    \n<li>사용량에 따른 요금 기준(월정액 별도)<br>* 통화<br> - ~270분까지: 무료 연결 제공(270분 통화 연결 이후 착신전환 상한정지)<br> - 상한정지 해지 이후~1,000분: 1.98원/1초 유료 과금<br> - 1,000분 초과 시: 당월 사용할 수 없음(다음 달 1일 자동 해제)\n                                    <br>※ 2025년 5월 1일부터 착신전환 서비스 이용 시 연결받는 번호가 SKT인 경우 통화에 대해서는 한도 제한 없이 착신전환이 제공됩니다. 그외 타 사업자 번호로의 착신전환의 경우 기존과 동일하게 통화 월 270분 한도 내에서 무료로 서비스 이용이 가능합니다.\n                                   <br> ※ 타 사업자 번호로의 착신전환 이용에 따른 기본 착신전환 통화 제공량 270분 소진 후에는 SKT/타 사업자 연결 구분없이 착신전환 상한정지가 적용되며, 이후 직접 착신전환 상한정지 해지 후 이용 시 SKT 번호로의 착신전환은 통화 무제한(무료), 타 사업자 번호로는 최대 1,000분(1.98원/1초 과금)까지 사용 가능합니다.<br>(단, 타 사업자 번호로의 착신전환 1,000분을 모두 사용하여 이용정지 상태가 되면, SKT/타 사업자 상관없이 착신전환 설정 및 이용이 불가함)</li>\n                                \n</ul>\n                                <h3>전화가 걸려와도 받을 수 없는 경우</h3>\n                                \n<ul>    \n                                    \n<li>휴대폰의 전원이 꺼져있는 경우</li>    \n                                    \n<li>전파음영지역 : NO SVC지역 등의 상황</li>    \n                                    \n<li>무응답:부득이 전화를 받을 수 없는 경우</li>    \n                                    \n<li>통화 중인 경우</li>\n                                \n</ul>\n                                <h3>참고사항</h3>\n                                \n<ul>\n                                    \n<li>자동연결 서비스와 착신전환(Voice only) 서비스의 차이점은?<br>- 자동연결 서비스 : 고객이 전화를 받을 수 없는 경우에만&nbsp;원하시는 전화로 연결됩니다.<br>- 착신전환(Voice only) 서비스 : 고객이 전화를 받을 수 있는지의&nbsp;여부를 떠나서 무조건 원하시는 전화로 연결이 됩니다.</li>    \n                                    \n<li>LTE 영상통화 시에는 해당 서비스를 지원하지 않습니다.</li>\n                                \n</ul>\n                            </div><!-- //##### admin 등록 영역 ##### --></div>\n                </div>\n            </div>"
  }
}