{
  "itemCode": "Z_SKT_1778385560069_346",
  "productName": "콜키퍼_O",
  "carrier": "SKT",
  "category": "통화_메시지",
  "description": "",
  "content": {
    "details": "<div class=\"divDetailInfoContents adaptive-visualization\" data-contentidx=\"1\" style=\"display: none;\">\n                <div class=\"adaptive-belt-1000\">\n                    <div class=\"adaptive-belt-w1000\"><div class=\"prCont-txt\"><ul> \n<li>월정액 550원(부가세 포함)</li><li>서비스 해지 시 요금은 일할 과금됩니다. </li></ul></div></div>\n                </div>\n            </div>",
    "usageGuidelines": "<div class=\"divDetailInfoContents adaptive-visualization\" data-contentidx=\"2\" style=\"display: none;\">\n                <div class=\"adaptive-belt-1000\">\n                    <div class=\"adaptive-belt-w1000\"><!-- ##### admin 등록 영역 ##### -->                            <div class=\"prCont-txt\">\n                                <table width=\"100%\" border=\"1\"><tbody><tr><th width=\"20%\"> 유형 </th><th width=\"30%\"> 가입/해지 채널 </th><th width=\"50%\"> 상세경로 </th></tr><!-- 220414 [MOZOP002-20307] -->\n                                        <tr><th rowspan=\"4\">가입</th><td>T World</td><td> 부가서비스 &gt; 통화/메시지 &gt; 콜키퍼_O </td></tr><tr><td>모바일 고객센터</td><td> 부가서비스 &gt; 통화/메시지 &gt; 콜키퍼_O </td></tr><tr><td>고객센터</td><td>02-1599-0011 / SK 텔레콤 휴대폰으로 지역번호없이 114</td></tr><tr><td>지점/대리점</td><td>-</td></tr><tr><th rowspan=\"5\">해지</th><td>T World</td><td> 부가서비스 &gt; 통화/메시지 &gt; 콜키퍼_O </td></tr><tr><td>모바일 고객센터</td><td> 부가서비스 &gt; 통화/메시지 &gt; 콜키퍼_O </td></tr><tr><td>고객센터</td><td>02-1599-0011 / SK 텔레콤 휴대폰으로 지역번호없이 114</td></tr><tr><td>지점/대리점</td><td>-</td></tr><tr><td>기타외부채널</td><td>T 통화매니저 앱 &gt; MY &gt; 콜키퍼_O 해지</td><!-- 230120 [MOZOP002-25157] -->\n                                        </tr><!-- //220414 [MOZOP002-20307] -->\n                                    </tbody></table>\n                            </div><!-- //##### admin 등록 영역 ##### --></div>\n                </div>\n            </div>",
    "notices": "<div class=\"divDetailInfoContents adaptive-visualization\" data-contentidx=\"3\" style=\"display: none;\">\n                <div class=\"adaptive-belt-1000\">\n                    <div class=\"adaptive-belt-w1000\"><!-- ##### admin 등록 영역 ##### -->                            <div class=\"prCont-txt\">\n                                <ul>\n                                    <li>발신번호는 100개까지 저장됩니다. <br>(단, 100건 초과 시에는 과거 저장번호부터 삭제되며, 30일 이상 정보에 대해서도 자동 삭제됩니다.)</li>\n                                    <li>발신번호가 비정상적인 경우(국제전화 등)에는 발신번호저장 서비스가 제공되지 않습니다.</li>\n                                    <li>같은 발신번호로 10분 이내 중복 수신된 경우 1건의 발신번호 정보만 제공됩니다.</li>\n                                    <li>전원이 꺼진 상태에서 들어온 콜키퍼 SMS의 경우 한달 이내 건에 대해서는 전원이 켜진 후 SMS 수신 및 확인이 가능합니다.<br>(단, 통화중, 음영지역(NPR), 배터리를 분리하여 수신이 불가한 상황에 대해서는 24시간이내 건에 대해서만 SMS통보 가능함)</li>\n                                    <li>콜키퍼에 저장된 발신번호정보는 콜키퍼 서비스 해지 시에 삭제되오니 유의하시기 바랍니다.</li>\n                                    <li>미수신된 발신번호 정보는 문자메시지(SMS), 온라인 T world, T 통화매니저 앱을 통해 확인할 수 있습니다.<br><!-- 230120 [MOZOP002-25157] -->\n                                        <p>\n                                            <!-- ※ 콜키퍼 수신내역 확인 ARS(15680) 서비스가 2018년 12월 31일부로 종료됩니다.<br> -->\n                                            온라인&nbsp; T world 및 T 통화매니저 앱을 통해서 수신내역을 확인하실 수 있습니다.</p><!-- 230120 [MOZOP002-25157] -->\n                                    </li>\n                                    <li>이용정지 및 일시정지 시 수신할 수 있는기간 중에는 사용 요금이 정상 부과됩니다.</li>\n                                    <li>비정상적인 경로나 7자리 미만의 번호로 수신된 통화에 대해서는 콜키퍼가 통보되지 않을 수 있습니다.</li>\n                                    <li>LTE 영상통화 시에는 해당 서비스를 지원하지 않습니다</li>\n                                    <li>단, 번호변경안내 서비스를 이용 중인 경우 변경 전 번호로 걸려온 전화와 통화중대기를 이용 중인 상태에서 걸려온 전화에 대해서는 콜키퍼 안내가 되지 않습니다.</li><!-- 220414 [MOZOP002-20307] -->\n                                </ul>\n                            </div><!-- //##### admin 등록 영역 ##### --></div>\n                </div>\n            </div>"
  }
}