{
  "itemCode": "Z_SKT_1778345791646_288",
  "productName": "발신금지",
  "carrier": "SKT",
  "category": "혜택_편의",
  "description": "",
  "content": {
    "details": "<div class=\"divDetailInfoContents adaptive-visualization\" data-contentidx=\"1\" style=\"display: none;\">\n                <div class=\"adaptive-belt-1000\">\n                    <div class=\"adaptive-belt-w1000\"><div class=\"prCont-txt\"><ul>     <li>이용요금 : 무료</li></ul></div></div>\n                </div>\n            </div>",
    "usageGuidelines": "<div class=\"divDetailInfoContents adaptive-visualization\" data-contentidx=\"2\" style=\"display: none;\">\n                <div class=\"adaptive-belt-1000\">\n                    <div class=\"adaptive-belt-w1000\">  <!-- ##### admin 등록 영역 ##### -->                            <div class=\"prCont-txt\">                                \n                                <table width=\"100%\" border=\"1\"><tbody><tr><th width=\"20%\"> 유형 </th><th width=\"30%\"> 가입/해지 채널 </th><th width=\"50%\"> 상세경로 </th></tr><!-- 220414 [MOZOP002-20307] -->\n                                        <tr><th rowspan=\"5\" scope=\"row\"> 가입 </th><td> T World </td><td> 부가서비스 &gt; 통화/메시지 &gt; 발신금지 </td></tr><tr><td> 모바일 고객센터 </td><td> 부가서비스 &gt; 통화/메시지 &gt; 발신금지 </td></tr><tr><td> 고객센터 </td><td> 02-1599-0011 / SK 텔레콤 휴대폰으로 지역번호없이 114 </td></tr><tr><td> 지점/대리점 </td><td> - </td></tr><tr><td> 기타외부채널 </td><td> T통화매니저앱 &gt; 발신금지 검색 &gt; 가입 </td></tr><tr><th rowspan=\"5\" scope=\"row\"> 해지 </th><td> T World </td><td> 부가서비스 &gt; 통화/메시지 &gt; 발신금지 </td></tr><tr><td> 모바일 고객센터 </td><td> 부가서비스 &gt; 통화/메시지 &gt; 발신금지 </td></tr><tr><td> 고객센터 </td><td> 02-1599-0011 / SK 텔레콤 휴대폰으로 지역번호없이 114 </td></tr><tr><td> 지점/대리점 </td><td> - </td></tr><tr><td> 기타외부채널 </td><td> T통화매니저앱 &gt; MY &gt; 발신금지 해지 </td></tr><!-- //220414 [MOZOP002-20307] -->\n                                    </tbody></table>                               \n                            </div><!-- ##### //admin 등록 영역 ##### --></div>\n                </div>\n            </div>\n<hr class=\"section-divider\">\n<div class=\"divDetailInfoContents adaptive-visualization\" data-contentidx=\"4\" style=\"display: none;\">\n                <div class=\"adaptive-belt-1000\">\n                    <div class=\"adaptive-belt-w1000\"><div class=\"prCont-txt\"><ul> <li>서비스 신청 후 자동 제공</li>  <li>발신 시 “지금 사용하신 전화는 고객의 사정에 의해 당분간 발신이 정지되어있습니다.”라는 안내멘트 제공</li></ul></div></div>\n                </div>\n            </div>",
    "notices": "<div class=\"divDetailInfoContents adaptive-visualization\" data-contentidx=\"3\" style=\"display: none;\">\n                <div class=\"adaptive-belt-1000\">\n                    <div class=\"adaptive-belt-w1000\"><div class=\"prCont-txt\"><ul>       <li>문자메시지(SMS,MMS) 서비스 수/발신 정상 이용할 수 있음(사용요금 정상 청구됨)</li> <li>기본료, 부가사용료, 각종 NATE정액제 등 신청되어 있는 월정액 정상 부과됨</li> <li>발신금지 신청 시 불필요한 부가 서비스는 취소 안내 필요</li> <li>JUNE 및 NATE, 3G 또는 LTE 데이터 접속이 불가함</li> <li>국제전화 발신금지 서비스와 함께 신청할 수 없음</li> <li>팅고객이 발신금지 신청 시 국제전화발신금지가 자동해지됨. (해지시 국제전화발신금지 자동설정)</li> <li> 미성년자 명의로 된 이동전화의 경우라도 법정대리인이 등록한 '발신금지 서비스'취소할 경우 법정대리인과의 '직접 통화' 후 취소할 수 있음</li> <li>발신금지 서비스 가입 시 자동로밍서비스는 제공되지 않음</li> <li>미성년자 명의인 경우 발신금지 해제는 온라인 T world에서 처리할 수 없음</li> <li>LTE 영상통화 시에는 해당 서비스를 지원하지 않습니다.</li></ul></div></div>\n                </div>\n            </div>"
  }
}