{
  "itemCode": "Z_LGU_1778169658638_496",
  "productName": "슈퍼스탁",
  "carrier": "LGU",
  "category": "PASS_정보",
  "description": "매일 로봇이 분석한 유망종목과 일간, 월간 포트폴리오 등 주식투자에 도움되는 정보를 문자메시지로 제공받는 서비스",
  "content": {
    "details": "<div class=\"c-page-section\">\n<p class=\"h2\">서비스 내용</p>\n\n<p class=\"h5 fw-m\">요금제</p>\n\n<div class=\"row c-table -mt-8n-2\">\n<table class=\"table b-table table-bordered\">\n\t<caption>요금제 : 월정액, 내용 에 대한 표</caption>\n\t<colgroup>\n\t\t<col width=\"360px\">\n\t\t<col width=\"auto\">\n\t</colgroup>\n\t<thead>\n\t\t<tr>\n\t\t\t<th scope=\"col\">월정액</th>\n\t\t\t<th scope=\"col\">내용</th>\n\t\t</tr>\n\t</thead>\n\t<tbody>\n\t\t<tr>\n\t\t\t<td>22,000원</td>\n\t\t\t<td class=\"c-cell-left\">\n\t\t\t<ul class=\"c-bullet-type-circle grow-1\">\n\t\t\t\t<li>매일 로봇이 분석한 유망 종목 1~2개를 추천</li>\n\t\t\t\t<li>실시간 거래현황, 재무제표, 기업가치 등을 기준으로 매매신호를 알려주는 포트폴리오 주 2~5회 제공</li>\n\t\t\t\t<li>실적 턴어라운드, 경영효율성, 재무안전성 등을 기준으로 매매신호를 알려주는 포트폴리오 월 1회 제공</li>\n\t\t\t\t<li>투자 가치를 판단할 수 있도록 유망 종목에 대한 기업 정보, 투자 지표 등 제공</li>\n\t\t\t</ul>\n\t\t\t</td>\n\t\t</tr>\n\t</tbody>\n</table>\n</div>\n\n<ul class=\"c-bullet-type-circle grow-1\">\n\t<li>부가세 포함 금액</li>\n\t<li>웹사이트 접속 시 가입한 요금제에 따라 데이터 이용료 발생</li>\n\t<li>별도의 해지 요청이 있을 때까지 매월 자동 연장</li>\n\t<li>로보어드바이저(robo-advisor)란? 로봇(robot)과 투자 전문가(advisor)의 합성어. 로봇이 빅데이터를 통해 포트폴리오를 관리해 주는 온라인 자산관리 서비스</li>\n</ul>\n</div>\n<hr class=\"section-divider\">\n<div class=\"c-page-section\">\n<p class=\"h2\">서비스 안내</p>\n\n<p class=\"h5\">서비스 특징</p>\n\n<ul class=\"c-bullet-type-circle grow-1\">\n\t<li>사용자가 입력한 투자성향을 바탕으로 종목을 추천하여 보다 객관적인 투자 정보를 얻을 수 있습니다.</li>\n\t<li>포트폴리오를 누적 운영하여, 매수 및 매도 시점을 정확히 제시합니다.</li>\n\t<li>종목별 상세정보를 제공하여 사용자의 투자성향 및 투자방법에 따라 전략을 세울 수 있습니다.</li>\n\t<li>일간, 월간 추천종목과 매매신호를 담은 포트폴리오를 문자메시지로 받을 수 있습니다.</li>\n</ul>\n\n<div class=\"-mt-8n-2\">\n<ul class=\"cv-thumb-list type-col-3n\">\n\t<li>\n\t<p class=\"th-thumb\"></p>\n\n\t<p class=\"th-tit\">오늘의 추천종목</p>\n\n\t<ul class=\"c-bullet-type-circle grow-1\">\n\t\t<li>평일, 오전 10시 인공지능 로봇이 분석한 유망 종목 1~2개를 추천받을 수 있습니다.</li>\n\t</ul>\n\t</li>\n\t<li>\n\t<p class=\"th-thumb\"></p>\n\n\t<p class=\"th-tit\">슈퍼스탁2호 포트폴리오 매매신호</p>\n\n\t<ul class=\"c-bullet-type-circle grow-1\">\n\t\t<li>주 2~5회 오전 11시 30분에 실시간 거래현황, 재무제표, 기업가치 등을 기준으로 매매신호를 받을 수 있습니다.</li>\n\t</ul>\n\t</li>\n\t<li>\n\t<p class=\"th-thumb\"></p>\n\n\t<p class=\"th-tit\">슈퍼스탁1호 포트폴리오 매매신호</p>\n\n\t<ul class=\"c-bullet-type-circle grow-1\">\n\t\t<li>월 1회, 오전 8시 30분에 실적 턴어라운드, 경영효율성, 재무안전성 등을 기준으로 매매신호를 받을 수 있습니다.</li>\n\t</ul>\n\t</li>\n</ul>\n</div>\n\n<p class=\"h5 -mt-8n-4\">주요 서비스</p>\n\n<div class=\"-mt-8n-2\">\n<ul class=\"cv-thumb-list type-col-3n\">\n\t<li>\n\t<p class=\"th-thumb\"></p>\n\n\t<p class=\"th-tit\">[종목추천]</p>\n\n\t<ul class=\"c-bullet-type-circle grow-1\">\n\t\t<li>매일 1~2 종목에 대한 매수 신호</li>\n\t\t<li>추천종목의 투자전략과 MVP점수, 기대수익률 제공</li>\n\t</ul>\n\t</li>\n\t<li>\n\t<p class=\"th-thumb\"></p>\n\n\t<p class=\"th-tit\">[포트폴리오-슈퍼스탁1호]</p>\n\n\t<ul class=\"c-bullet-type-circle grow-1\">\n\t\t<li>월 1회, 20개 종목으로 구성된 포트폴리오 제시</li>\n\t\t<li>편입 및 제외 종목 상세 확인 가능</li>\n\t\t<li>수익률 확인 가능</li>\n\t</ul>\n\t</li>\n\t<li>\n\t<p class=\"th-thumb\"></p>\n\n\t<p class=\"th-tit\">[포트폴리오-슈퍼스탁2호]</p>\n\n\t<ul class=\"c-bullet-type-circle grow-1\">\n\t\t<li>주 2~5회 1~2종목에 대한 매매 신호</li>\n\t\t<li>매수 또는 매도할 종목 상세 확인 가능</li>\n\t\t<li>수익률 확인 가능</li>\n\t</ul>\n\t</li>\n</ul>\n</div>\n\n<div class=\"-mt-8n-2\">\n<ul class=\"cv-thumb-list type-col-3n\">\n\t<li>\n\t<p class=\"th-thumb\"></p>\n\n\t<p class=\"th-tit\">[투자점수]</p>\n\n\t<ul class=\"c-bullet-type-circle grow-1\">\n\t\t<li>약 1,890여개 종목을 분석하여, 투자매력도 제공</li>\n\t\t<li>매일 투자점수 순으로 종목 공개</li>\n\t</ul>\n\t</li>\n\t<li>&nbsp;</li>\n\t<li>&nbsp;</li>\n</ul>\n</div>\n</div>\n<hr class=\"section-divider\">\n<div class=\"c-accordion-group\"><div variant=\"primary\" class=\"c-accordion-header collapsed\" role=\"button\" tabindex=\"0\" aria-expanded=\"false\" aria-controls=\"_uid_427_2\" style=\"overflow-anchor: none;\"><strong class=\"w-auto\">[슈퍼스탁] 이용요금은 얼마인가요?</strong> <div class=\"acc-toggle\"><i class=\"when-open\"></i> <i class=\"when-closed\"></i></div></div> <div id=\"_uid_427_2\" class=\"collapse\" style=\"display: none;\"><div class=\"card\"><!----><!----><div class=\"card-body\"><!----><!----><div class=\"contentsWrap\"><p>부가세 포함하여 월 22,000원입니다. <br>U+ 휴대폰 요금에 합산 청구되며, 중간에 해지하는 경우 사용일수에 따라 계산됩니다.</p></div></div><!----><!----></div></div></div>\n<hr class=\"section-divider\">\n<div class=\"c-accordion-group\"><div variant=\"primary\" class=\"c-accordion-header collapsed\" role=\"button\" tabindex=\"0\" aria-expanded=\"false\" aria-controls=\"_uid_427_4\" style=\"overflow-anchor: none;\"><strong class=\"w-auto\">[슈퍼스탁] 주요 기능이 무엇인가요?</strong> <div class=\"acc-toggle\"><i class=\"when-open\"></i> <i class=\"when-closed\"></i></div></div> <div id=\"_uid_427_4\" class=\"collapse\" style=\"display: none;\"><div class=\"card\"><!----><!----><div class=\"card-body\"><!----><!----><div class=\"contentsWrap\"><p>▶ 주식 매수 및 매도 시점을 알기 힘든 초급 투자자를 위해 일, 월 단위 포트폴리오를 제공합니다.<br>\n- 슈퍼스탁2호 : 일주일에 L34, 매매 종목 1~2개를 문자메시지로 안내<br>\n- 슈퍼스탁1호 : 매월 주식거래소 첫 개장일에 매매 종목 20건을 문자메시지로 안내<br>\n▶ 종목 발굴이 어려운 초·중급 투자자를 위해 매일 추천 종목 1~2개를 문자메시지로 제공합니다.<br>▶ 장기적으로 가치투자 할 수 있도록 유망 종목에 대한 기업 정보 및 주식 시황 정보를 제공합니다.</p></div></div><!----><!----></div></div></div>\n<hr class=\"section-divider\">\n<div class=\"c-accordion-group\"><div variant=\"primary\" class=\"c-accordion-header collapsed\" role=\"button\" tabindex=\"0\" aria-expanded=\"false\" aria-controls=\"_uid_427_6\" style=\"overflow-anchor: none;\"><strong class=\"w-auto\">[슈퍼스탁] 이용요금은 어떻게 청구되나요?</strong> <div class=\"acc-toggle\"><i class=\"when-open\"></i> <i class=\"when-closed\"></i></div></div> <div id=\"_uid_427_6\" class=\"collapse\" style=\"display: none;\"><div class=\"card\"><!----><!----><div class=\"card-body\"><!----><!----><div class=\"contentsWrap\"><p>다음 달 휴대폰 요금에 부가세를 포함 월 22,000원이 청구됩니다. <br>월 중간에 가입 및 해지하는 경우 사용일수에 따라 계산됩니다.</p></div></div><!----><!----></div></div></div>",
    "usageGuidelines": "<div class=\"c-accordion-group\"><div variant=\"primary\" class=\"c-accordion-header collapsed\" role=\"button\" tabindex=\"0\" aria-expanded=\"false\" aria-controls=\"_uid_425_0\" style=\"overflow-anchor: none;\"><div class=\"row\" style=\"width: 100%;\"><div class=\"col\"><strong>이용방법</strong></div> <!----></div> <div class=\"acc-toggle\"><i class=\"when-open\"></i> <i class=\"when-closed\"></i></div></div> <div id=\"_uid_425_0\" class=\"collapse\" style=\"display: none;\"><div class=\"card\"><!----><!----><div class=\"card-body\"><!----><!----><div class=\"cv-html-wrap\"><!-- CVHTML : 이용방법 -->\n<div class=\"pc-cv-box\">\n<div class=\"cv-use-wrap\">\n<ul class=\"c-bullet-type-circle grow-1\">\n\t<li>하루 최대 3회 추천종목 및 매수, 매도 종목을 문자메시지로 받을 수 있습니다.</li>\n\t<li>문자메시지 내 인터넷 주소(url)로 접속하면 기업정보, 실적 등 상세 정보를 확인할 수 있습니다.</li>\n</ul>\n\n<div class=\"m-swiper swiper_swiper2-3 swiperPc-nav -mt-8n-4\">\n<div class=\"swiper-container swiper-container-initialized swiper-container-horizontal\">\n<div class=\"swiper-wrapper\" style=\"transition-duration: 0ms;\">\n<div class=\"swiper-slide\">\n<ul class=\"cv-thumb-list type-step\">\n\t<li>\n\t<p class=\"th-label\">1단계</p>\n\n\t<p class=\"th-thumb\"></p>\n\n\t<p class=\"th-cont\">문자메시지 내 인터넷주소(url)를 누르세요.</p>\n\t</li>\n\t<li>\n\t<p class=\"th-label\">2단계</p>\n\n\t<p class=\"th-thumb\"></p>\n\n\t<p class=\"th-cont\">가입한 휴대폰번호 및 보안문자를 입력하고, [인증문자 요청]을 누르세요.</p>\n\t</li>\n\t<li>\n\t<p class=\"th-label\">3단계</p>\n\n\t<p class=\"th-thumb\"></p>\n\n\t<p class=\"th-cont\">인증번호 6자리를 입력한 후 [로그인]을 누르세요.</p>\n\t</li>\n</ul>\n</div>\n\n<div class=\"swiper-slide\">\n<ul class=\"cv-thumb-list type-step\">\n\t<li>\n\t<p class=\"th-label\">4단계</p>\n\n\t<p class=\"th-thumb\"></p>\n\n\t<p class=\"th-cont\">[종목추천], [슈퍼스탁1호], [슈퍼스탁2호] 메뉴등 자세히 알고 싶은 정보를 누르세요.</p>\n\t</li>\n\t<li>\n\t<p class=\"th-label\">5단계</p>\n\n\t<p class=\"th-thumb\"></p>\n\n\t<p class=\"th-cont\">자세한 정보를 확인할 수 있습니다.</p>\n\t</li>\n</ul>\n</div>\n</div>\n<button class=\"swiper-button-prev\" type=\"button\" tabindex=\"0\" role=\"button\" aria-label=\"이전 슬라이드로 이동\" aria-disabled=\"false\"><span class=\"is-blind\">이전 슬라이드로 가기</span></button><button class=\"swiper-button-next\" type=\"button\" tabindex=\"0\" role=\"button\" aria-label=\"다음 슬라이드로 이동\" aria-disabled=\"false\"><span class=\"is-blind\">다음 슬라이드로 가기</span></button><span class=\"swiper-notification\" aria-live=\"assertive\" aria-atomic=\"true\"></span></div>\n</div>\n</div>\n</div>\n\n\n<!-- //CVHTML : 이용방법 --></div>\n <!----> <!----></div><!----><!----></div></div></div>\n<hr class=\"section-divider\">\n<div class=\"c-accordion-group\"><div variant=\"primary\" class=\"c-accordion-header collapsed\" role=\"button\" tabindex=\"0\" aria-expanded=\"false\" aria-controls=\"_uid_425_1\" style=\"overflow-anchor: none;\"><div class=\"row\" style=\"width: 100%;\"><div class=\"col\"><strong>가입 및 해지</strong></div> <!----></div> <div class=\"acc-toggle\"><i class=\"when-open\"></i> <i class=\"when-closed\"></i></div></div> <div id=\"_uid_425_1\" class=\"collapse\" style=\"display: none;\"><div class=\"card\"><!----><!----><div class=\"card-body\"><!----><!----><div class=\"cv-html-wrap\"><!-- CVHTML : 가입 및 해지 -->\n<div class=\"pc-cv-box\">\n<div class=\"cv-use-wrap\">\n<p class=\"h4\">서비스 가입하기</p>\n\n<div class=\"m-swiper swiper_swiper2-3 swiperPc-nav\">\n<div class=\"swiper-container swiper-container-initialized swiper-container-horizontal\">\n<div class=\"swiper-wrapper\" style=\"transition-duration: 0ms;\">\n<div class=\"swiper-slide\">\n<ul class=\"cv-thumb-list type-step\">\n\t<li>\n\t<p class=\"th-label\">1단계</p>\n\n\t<p class=\"th-thumb\"></p>\n\n\t<p class=\"th-cont\">슈퍼스탁 홈페이지 <a class=\"underline\" href=\"https://super.stockn.kr\" target=\"_blank\" title=\"새창열림\">https://super.stockn.kr</a>에서 [종목 추천 받기]를 누르거나 제휴사 사이트에서 슈퍼스탁 배너를 누르세요.</p>\n\t</li>\n\t<li>\n\t<p class=\"th-label\">2단계</p>\n\n\t<p class=\"th-thumb\"></p>\n\n\t<p class=\"th-cont\">휴대폰 번호를 입력하고 [전체 동의]를 체크하세요. [슈퍼스탁 유료가입하기]를 누르면 문자메시지로 인증번호가 도착합니다.</p>\n\t</li>\n\t<li>\n\t<p class=\"th-label\">3단계</p>\n\n\t<p class=\"th-thumb\"></p>\n\n\t<p class=\"th-cont\">인증번호 6자리를 입력한 후 [슈퍼스탁 유료가입하기]를 다시 누르세요.</p>\n\t</li>\n</ul>\n</div>\n\n<div class=\"swiper-slide\">\n<ul class=\"cv-thumb-list type-step\">\n\t<li>\n\t<p class=\"th-label\">4단계</p>\n\n\t<p class=\"th-thumb\"></p>\n\n\t<p class=\"th-cont\">화면에 가입완료 메시지가 나타납니다.</p>\n\t</li>\n</ul>\n</div>\n</div>\n<button class=\"swiper-button-prev\" type=\"button\" tabindex=\"0\" role=\"button\" aria-label=\"이전 슬라이드로 이동\" aria-disabled=\"false\"><span class=\"is-blind\">이전 슬라이드로 가기</span></button><button class=\"swiper-button-next\" type=\"button\" tabindex=\"0\" role=\"button\" aria-label=\"다음 슬라이드로 이동\" aria-disabled=\"false\"><span class=\"is-blind\">다음 슬라이드로 가기</span></button><span class=\"swiper-notification\" aria-live=\"assertive\" aria-atomic=\"true\"></span></div>\n</div>\n</div>\n</div>\n\n\n<!-- //CVHTML : 가입 및 해지  --></div>\n <!----> <!----></div><!----><!----></div></div></div>\n<hr class=\"section-divider\">\n<div class=\"c-accordion-group\"><div variant=\"primary\" class=\"c-accordion-header collapsed\" role=\"button\" tabindex=\"0\" aria-expanded=\"false\" aria-controls=\"_uid_425_2\" style=\"overflow-anchor: none;\"><div class=\"row\" style=\"width: 100%;\"><div class=\"col\"><strong>유의사항</strong></div> <!----></div> <div class=\"acc-toggle\"><i class=\"when-open\"></i> <i class=\"when-closed\"></i></div></div> <div id=\"_uid_425_2\" class=\"collapse\" style=\"display: none;\"><div class=\"card\"><!----><!----><div class=\"card-body\"><!----><!----><div class=\"cv-html-wrap\"><!-- CVHTML : 유의사항 -->\n<div class=\"pc-cv-box\">\n<ul class=\"c-bullet-type-circle grow-1\">\n\t<li>서비스 이용 중 일반폰 또는 선불 요금제, 알뜰폰으로 변경하면 서비스가 자동 해지됩니다.</li>\n\t<li>일시적인 통신 장애로 문자메시지를 받지 못할 수 있습니다.</li>\n\t<li>2일 이상 문자메시지가 오지 않는 경우에는 스팸 문자함을 확인 후, 스팸 해제를 해주세요. 스팸 문자함에도 없는 경우 슈퍼스탁 고객센터 1599-7084 로 연락 주세요.</li>\n\t<li>서비스를 해지하려면 슈퍼스탁 고객센터 1599-7084 또는 LG유플러스 고객센터 114로 문의하세요.</li>\n\t<li>월 중간에 가입 또는 해지하는 경우, 사용 일수에 따라 이용요금을 계산합니다.</li>\n\t<li>슈퍼스탁은 투자 참고 사항만 제공할 뿐, 투자 및 주식거래를 권유하지 않습니다.</li>\n\t<li>투자판단에 대한 최종 책임은 이용자에게 있습니다.</li>\n</ul>\n\n<p class=\"h4 fw-m -mt-8n-4\">문의안내</p>\n\n<ul class=\"c-bullet-type-circle grow-1\">\n\t<li>서비스 가입 및 해지 등 이용문의: 휴대폰에서 114(무료), 1544-0010(유료)</li>\n\t<li>서비스 장애 및 기술문의: 슈퍼스탁 고객센터 1599-7084(무료)</li>\n</ul>\n</div>\n\n\n<!-- //CVHTML : 유의사항 --></div>\n <!----> <!----></div><!----><!----></div></div></div>\n<hr class=\"section-divider\">\n<div class=\"c-accordion-group\"><div variant=\"primary\" class=\"c-accordion-header collapsed\" role=\"button\" tabindex=\"0\" aria-expanded=\"false\" aria-controls=\"_uid_427_7\" style=\"overflow-anchor: none;\"><strong class=\"w-auto\">[슈퍼스탁] 가입 안내 문자를 여러 번 받아도 괜찮나요?</strong> <div class=\"acc-toggle\"><i class=\"when-open\"></i> <i class=\"when-closed\"></i></div></div> <div id=\"_uid_427_7\" class=\"collapse\" style=\"display: none;\"><div class=\"card\"><!----><!----><div class=\"card-body\"><!----><!----><div class=\"contentsWrap\"><p>여러 번 받아도 괜찮습니다.<br>\n고객이 요청한 문자메시지를 정상 발송했는지 바로 확인하지 못할 경우, 다시 보내드리고 있습니다. <br>고객의 요청에 빠르게 응대하기 위함이니 같은 문자를 2번 이상 받는 고객들의 양해 부탁드립니다.</p></div></div><!----><!----></div></div></div>",
    "notices": "<div class=\"c-accordion-group\"><div variant=\"primary\" class=\"c-accordion-header collapsed\" role=\"button\" tabindex=\"0\" aria-expanded=\"false\" aria-controls=\"_uid_425_2\" style=\"overflow-anchor: none;\"><div class=\"row\" style=\"width: 100%;\"><div class=\"col\"><strong>유의사항</strong></div> <!----></div> <div class=\"acc-toggle\"><i class=\"when-open\"></i> <i class=\"when-closed\"></i></div></div> <div id=\"_uid_425_2\" class=\"collapse\" style=\"display: none;\"><div class=\"card\"><!----><!----><div class=\"card-body\"><!----><!----><div class=\"cv-html-wrap\"><!-- CVHTML : 유의사항 -->\n<div class=\"pc-cv-box\">\n<ul class=\"c-bullet-type-circle grow-1\">\n\t<li>서비스 이용 중 일반폰 또는 선불 요금제, 알뜰폰으로 변경하면 서비스가 자동 해지됩니다.</li>\n\t<li>일시적인 통신 장애로 문자메시지를 받지 못할 수 있습니다.</li>\n\t<li>2일 이상 문자메시지가 오지 않는 경우에는 스팸 문자함을 확인 후, 스팸 해제를 해주세요. 스팸 문자함에도 없는 경우 슈퍼스탁 고객센터 1599-7084 로 연락 주세요.</li>\n\t<li>서비스를 해지하려면 슈퍼스탁 고객센터 1599-7084 또는 LG유플러스 고객센터 114로 문의하세요.</li>\n\t<li>월 중간에 가입 또는 해지하는 경우, 사용 일수에 따라 이용요금을 계산합니다.</li>\n\t<li>슈퍼스탁은 투자 참고 사항만 제공할 뿐, 투자 및 주식거래를 권유하지 않습니다.</li>\n\t<li>투자판단에 대한 최종 책임은 이용자에게 있습니다.</li>\n</ul>\n\n<p class=\"h4 fw-m -mt-8n-4\">문의안내</p>\n\n<ul class=\"c-bullet-type-circle grow-1\">\n\t<li>서비스 가입 및 해지 등 이용문의: 휴대폰에서 114(무료), 1544-0010(유료)</li>\n\t<li>서비스 장애 및 기술문의: 슈퍼스탁 고객센터 1599-7084(무료)</li>\n</ul>\n</div>\n\n\n<!-- //CVHTML : 유의사항 --></div>\n <!----> <!----></div><!----><!----></div></div></div>"
  }
}